gedi/__init__.py
gedi/augmentation.py
gedi/benchmark.py
gedi/config.py
gedi/features.py
gedi/generator.py
gedi/plotter.py
gedi/run.py
gedi/utils/__init__.py
gedi/utils/column_mappings.py
gedi/utils/default_argparse.py
gedi/utils/execute_grid_experiments.py
gedi/utils/io_helpers.py
gedi/utils/matrix_tools.py
gedi/utils/param_keys/__init__.py
gedi/utils/param_keys/augmentation.py
gedi/utils/param_keys/benchmark.py
gedi/utils/param_keys/features.py
gedi/utils/param_keys/generator.py
gedi/utils/param_keys/plotter.py
utils/__init__.py
utils/config_fabric.py
utils/merge_csvs.py
utils/merge_jsons.py
gedi-1.0.3.dist-info/LICENSE
gedi-1.0.3.dist-info/METADATA
gedi-1.0.3.dist-info/WHEEL
gedi-1.0.3.dist-info/top_level.txt
gedi-1.0.3.dist-info/RECORD
