Metadata-Version: 2.2
Name: gedi
Version: 1.0.3
Summary: Generating Event Data with Intentional Features for Benchmarking Process Mining
Home-page: https://github.com/lmu-dbs/gedi.git
Author: Andrea Maldonado
Author-email: andreamalher.works@gmail.com
License: MIT
Classifier: Development Status :: 3 - Alpha
Classifier: Intended Audience :: Science/Research
Classifier: Topic :: Software Development
Classifier: License :: OSI Approved :: MIT License
Classifier: Programming Language :: Python :: 3.9
License-File: LICENSE
Requires-Dist: ConfigSpace==0.7.1
Requires-Dist: imblearn==0.0
Requires-Dist: Levenshtein==0.23.0
Requires-Dist: matplotlib==3.8.4
Requires-Dist: numpy==1.26.4
Requires-Dist: pandas==2.2.2
Requires-Dist: pm4py==2.7.2
Requires-Dist: scikit-learn==1.2.2
Requires-Dist: scipy==1.13.0
Requires-Dist: seaborn==0.13.2
Requires-Dist: smac==2.0.2
Requires-Dist: tqdm==4.65.0
Requires-Dist: streamlit-toggle-switch>=1.0.2
Requires-Dist: click==8.1.7
Requires-Dist: cloudpickle==3.0.0
Requires-Dist: configspace==0.7.1
Requires-Dist: cvxopt==1.3.2
Requires-Dist: dask==2024.2.1
Requires-Dist: dask-jobqueue==0.8.5
Requires-Dist: deprecation==2.1.0
Requires-Dist: distributed==2024.2.1
Requires-Dist: emcee==3.1.4
Requires-Dist: feeed>=1.3.2
Requires-Dist: fsspec==2024.2.0
Requires-Dist: imbalanced-learn==0.12.0
Requires-Dist: imblearn==0.0
Requires-Dist: importlib-metadata==7.0.1
Requires-Dist: intervaltree==3.1.0
Requires-Dist: jinja2==3.1.3
Requires-Dist: levenshtein==0.23.0
Requires-Dist: locket==1.0.0
Requires-Dist: lxml==5.1.0
Requires-Dist: markupsafe==2.1.5
Requires-Dist: more-itertools==10.2.0
Requires-Dist: msgpack==1.0.8
Requires-Dist: networkx==3.2.1
Requires-Dist: numpy==1.26.4
Requires-Dist: pandas>=2.0.0
Requires-Dist: partd==1.4.1
Requires-Dist: pm4py==2.7.2
Requires-Dist: psutil==5.9.8
Requires-Dist: pydotplus==2.0.2
Requires-Dist: pynisher==1.0.10
Requires-Dist: pyrfr==0.9.0
Requires-Dist: pyyaml==6.0.1
Requires-Dist: rapidfuzz==3.6.1
Requires-Dist: regex==2023.12.25
Requires-Dist: scikit-learn==1.2.2
Requires-Dist: seaborn==0.13.2
Requires-Dist: smac==2.0.2
Requires-Dist: sortedcontainers==2.4.0
Requires-Dist: stringdist==1.0.9
Requires-Dist: tblib==3.0.0
Requires-Dist: toolz==0.12.1
Requires-Dist: tqdm==4.65.0
Requires-Dist: typing-extensions==4.10.0
Requires-Dist: urllib3==2.2.1
Requires-Dist: zict==3.0.0
Dynamic: author
Dynamic: author-email
Dynamic: classifier
Dynamic: description
Dynamic: description-content-type
Dynamic: home-page
Dynamic: license
Dynamic: requires-dist
Dynamic: summary
